{
  "lesson_id": "ta_13_vowel_markers_4",
  "language": "Tamil",
  "title": "Vowel Markers IV",
  "subtitle": "O, Oo, and Au",
  "description": "Learn the 'surrounding' vowel markers that have components both before and after the consonant.",
  "estimated_minutes": 25,
  "cefr_level": "A0",
  "tags": ["script", "vowel-markers", "basics"],
  "skills_learned": [
    "Recognizing the short 'o' marker",
    "Recognizing the long 'oo' marker",
    "Recognizing the 'au' marker",
    "Reading syllables like கொ, கோ, and கௌ"
  ],
  "steps": [
    {
      "type": "content",
      "step_title": "Surrounding Markers",
      "content_markdown": "## Both Sides\n\nThe final set of vowel markers are combinations. They place one symbol **before** the consonant and another **after** it. They 'hug' the consonant!",
      "step_title": "Surrounding Markers"
    },
    {
      "type": "content",
      "step_title": "The Short 'O' Marker",
      "content_markdown": "## The Short 'O' Marker: ொ\n\nThis is a combination of the short 'e' marker (**ெ**) and the 'aa' marker (**ா**).\n\n| Combination | Result | Sound |\n|-------------|--------|-------|\n| **க** + **ஒ** | **கொ** | ko |\n| **ம** + **ஒ** | **மொ** | mo |\n| **ப** + **ஒ** | **பொ** | po |",
      "step_title": "The Short 'O' Marker"
    },
    {
      "type": "multiple_choice",
      "id": "q1",
      "question": "How is **பொ** pronounced?",
      "options": ["po", "poo", "pe", "pa"],
      "correct_answer": "po",
      "feedback": "Correct! The markers on both sides create the short 'o' sound.",
      "step_title": "Identify பொ Sound"
    },
    {
      "type": "content",
      "step_title": "The Long 'Oo' Marker",
      "content_markdown": "## The Long 'Oo' Marker: ோ\n\nThis is a combination of the long 'ee' marker (**ே**) and the 'aa' marker (**ா**).\n\n| Combination | Result | Sound |\n|-------------|--------|-------|\n| **க** + **ஓ** | **கோ** | koo |\n| **ம** + **ஓ** | **மோ** | moo |\n| **ப** + **ஓ** | **போ** | poo |",
      "step_title": "The Long 'Oo' Marker"
    },
    {
      "type": "multiple_choice",
      "id": "q2",
      "question": "How is **கோ** pronounced?",
      "options": ["ko", "koo", "ke", "ka"],
      "correct_answer": "koo",
      "feedback": "Perfect! This combination adds the long 'oo' sound.",
      "step_title": "Identify கோ Sound"
    },
    {
      "type": "content",
      "step_title": "The 'Au' Marker",
      "content_markdown": "## The 'Au' Marker: ௌ\n\nThis is a combination of the short 'e' marker (**ெ**) and a special 'L-shaped' marker (**ள**).\n\n| Combination | Result | Sound |\n|-------------|--------|-------|\n| **க** + **ஔ** | **கௌ** | kau |\n| **ம** + **ஔ** | **மௌ** | mau |\n| **ப** + **ஔ** | **பௌ** | pau |",
      "step_title": "The 'Au' Marker"
    },
    {
      "type": "multiple_choice",
      "id": "q3",
      "question": "How is **கௌ** pronounced?",
      "options": ["ko", "kau", "kai", "ku"],
      "correct_answer": "kau",
      "feedback": "Excellent! This combination adds the 'au' sound.",
      "step_title": "Identify கௌ Sound"
    },
    {
      "type": "content",
      "step_title": "Reading Practice",
      "content_markdown": "## Read the Words\n\nTry reading these combinations:\n- **கொ** (ko) + **டு** (Du) = **கொடு** (kodu - *give*)\n- **கோ** (koo) + **ல** (la) + **ம்** (m) = **கோலம்** (koolam - *pattern*)\n- **மௌ** (mau) + **ன** (na) + **ம்** (m) = **மௌனம்** (maunam - *silence*)",
      "step_title": "Reading Practice"
    },
    {
      "type": "multiple_choice",
      "id": "q4",
      "question": "How is **கொடு** pronounced?",
      "options": ["kodu", "kotu", "godu", "gotu"],
      "correct_answer": "kodu",
      "feedback": "Correct! **கொ** (ko) + **டு** (Du) = **kodu**. Note the softening of the 'T' to 'd'.",
      "step_title": "Read கொடு"
    },
    {
      "type": "free_response",
      "id": "q5",
      "question": "Write the sound of **மோ** in English letters.",
      "ai_grading": false,
      "accepted_responses": ["moo"],
      "hint": "It's 'm' with the long 'oo' marker.",
      "step_title": "Write the Sound"
    },
    {
      "type": "free_response",
      "id": "q6",
      "question": "Write the sound of **பௌ** in English letters.",
      "ai_grading": false,
      "accepted_responses": ["pau"],
      "hint": "It's 'p' with the 'au' marker.",
      "step_title": "Write the Sound"
    },
    {
      "type": "multiple_choice",
      "id": "q7",
      "question": "Which of these is 'so'?",
      "options": ["சொ", "சோ", "சௌ", "செ"],
      "correct_answer": "சொ",
      "feedback": "Correct! **சொ** is 'so'.",
      "step_title": "Identify சொ"
    },
    {
      "type": "free_response",
      "id": "q8",
      "question": "Type the sound of **லோ**",
      "ai_grading": false,
      "accepted_responses": ["loo"],
      "hint": "It's 'la' with long 'oo'.",
      "step_title": "Identify லோ"
    },
    {
      "type": "multiple_choice",
      "id": "q9",
      "question": "What components make up the **ோ** (long oo) marker?",
      "options": ["ெ and ா", "ே and ா", "ெ and ள", "ா and ி"],
      "correct_answer": "ே and ா",
      "feedback": "Correct! Long e marker + aa marker = long oo marker.",
      "step_title": "Marker Components"
    },
    {
      "type": "content",
      "step_title": "Visual Summary",
      "content_markdown": "## Marker Recap\n\n- **ொ** = short o (both sides)\n- **ோ** = long oo (both sides)\n- **ௌ** = au (both sides)",
      "step_title": "Visual Summary"
    },
    {
      "type": "multiple_choice",
      "id": "q10",
      "question": "Which of these is the long 'oo' version of **கொ**?",
      "options": ["கௌ", "கோ", "கா", "கி"],
      "correct_answer": "கோ",
      "feedback": "Correct! **கோ** is the long 'oo' version.",
      "step_title": "Final Check"
    }
  ]
}