{
  "lesson_id": "ta_16_special_retroflexes",
  "language": "Tamil",
  "title": "Special Retroflexes",
  "subtitle": "Zha, Ra, and Na",
  "description": "Master the pronunciation and distinction of Tamil's most unique letters.",
  "estimated_minutes": 25,
  "cefr_level": "A0",
  "tags": ["script", "pronunciation", "advanced"],
  "skills_learned": [
    "Perfecting the 'zha' sound",
    "Distinguishing between ர (ra) and ற (Ra)",
    "Distinguishing between ந, ண, and ன",
    "Reading words with these special characters"
  ],
  "steps": [
    {
      "type": "content",
      "step_title": "Tamil's Pride",
      "content_markdown": "## Unique Sounds\n\nTamil has several sounds that are rare in other languages. Mastering these is the key to sounding like a native speaker!"
    },
    {
      "type": "content",
      "step_title": "The Magic of ழ",
      "content_markdown": "## ழ - The 'Zha'\n\nWe saw this briefly. It's a 'retroflex approximant'. Curl your tongue back but **don't touch anything**. The air flows around the sides.\n\n- **தமிழ்** (ta-mi-zh) = Tamil\n- **வாழை** (vaa-zhai) = Banana"
    },
    {
      "type": "multiple_choice",
      "id": "q1",
      "step_title": "Pronounce ழ",
      "question": "Which of these is the correct way to say **ழ**?",
      "options": ["Tongue touches teeth", "Tongue curls back but doesn't touch roof", "Tongue touches the roof", "Lips touch"],
      "correct_answer": "Tongue curls back but doesn't touch roof",
      "feedback": "Correct! That 'floating' tongue creates the unique 'zha' sound."
    },
    {
      "type": "content",
      "step_title": "The Two R sounds",
      "content_markdown": "## ர (ra) vs ற (Ra)\n\n- **ர** is soft, like in **road**.\n- **ற** is hard and trilled, like in Spanish **perro**.\n\nExample:\n- **அரம்** (aram) = File (tool)\n- **அறம்** (aRam) = Virtue/Righteousness"
    },
    {
      "type": "multiple_choice",
      "id": "q2",
      "step_title": "Compare R sounds",
      "question": "Which R sound is harder and trilled?",
      "options": ["ர", "ற", "ல", "ழ"],
      "correct_answer": "ற",
      "feedback": "Perfect! **ற** is the hard, trilled 'R'."
    },
    {
      "type": "content",
      "step_title": "The Three N sounds",
      "content_markdown": "## ந vs ண vs ன\n\nTamil has three 'n' sounds!\n1. **ந** (Dental): Tongue touches teeth. Used at the **start** of words.\n2. **ண** (Retroflex): Tongue curls back. Used in the **middle/end**.\n3. **ன** (Alveolar): Tongue touches the ridge behind teeth. Used in the **middle/end**."
    },
    {
      "type": "multiple_choice",
      "id": "q3",
      "step_title": "Start of Words",
      "question": "Which 'n' is typically used to start a word?",
      "options": ["ந", "ண", "ன", "ம"],
      "correct_answer": "ந",
      "feedback": "Correct! **ந** is the dental 'n' used at the beginning."
    },
    {
      "type": "content",
      "step_title": "The Three L sounds",
      "content_markdown": "## ல vs ள vs ழ\n\n1. **ல** (Standard): Tongue touches teeth.\n2. **ள** (Retroflex): Tongue curls back to the roof.\n3. **ழ** (Special): Tongue curls back but doesn't touch.\n\nExample:\n- **காலி** (kaali) = Empty\n- **காளி** (kaaLi) = Goddess Kali\n- **காழி** (kaazhi) = A place name"
    },
    {
      "type": "multiple_choice",
      "id": "q4",
      "step_title": "Identify ள",
      "question": "What kind of 'L' is **ள**?",
      "options": ["Standard L", "Retroflex L (tongue touches roof)", "Special L (tongue doesn't touch)", "Nasal L"],
      "correct_answer": "Retroflex L (tongue touches roof)",
      "feedback": "Excellent! **ள** is the retroflex 'L'."
    },
    {
      "type": "free_response",
      "id": "q5",
      "step_title": "Identify the Letter",
      "question": "Which letter represents the hard trilled 'R'?",
      "ai_grading": false,
      "accepted_responses": ["ற"],
      "hint": "It looks like a small 'p' with a tail or a hook."
    },
    {
      "type": "free_response",
      "id": "q6",
      "step_title": "Identify the Sound",
      "question": "In the word **பழம்** (pazham), what is the final sound of the second syllable?",
      "ai_grading": false,
      "accepted_responses": ["zha", "zham"],
      "hint": "It's the special Tamil sound."
    },
    {
      "type": "multiple_choice",
      "id": "q7",
      "step_title": "Compare ன and ண",
      "question": "Which 'n' is retroflex (tongue curled back)?",
      "options": ["ந", "ன", "ண", "ம"],
      "correct_answer": "ண",
      "feedback": "Correct! **ண** is the retroflex 'N'.",
      "step_title": "Compare ன and ண"
    },
    {
      "type": "free_response",
      "id": "q8",
      "step_title": "Identify 'Standard' L",
      "question": "Type the letter for the standard 'L' sound.",
      "ai_grading": false,
      "accepted_responses": ["ல"],
      "hint": "It's the one where the tongue touches the teeth.",
      "step_title": "Identify 'Standard' L"
    },
    {
      "type": "multiple_choice",
      "id": "q9",
      "step_title": "Rhotic Distinction",
      "question": "Which letter is used in the word for virtue (**அறம்**)?",
      "options": ["ர", "ற", "ல", "ழ"],
      "correct_answer": "ற",
      "feedback": "Perfect! Virtue is **அறம்** with the hard trilled R.",
      "step_title": "Rhotic Distinction"
    },
    {
      "type": "content",
      "step_title": "Final Comparison",
      "content_markdown": "## Summary Table\n\n| Sound Type | Standard | Retroflex | Special |\n|------------|----------|-----------|---------|\n| **Nasal** | ந (na) | ண ($N$a) | ன (na) |\n| **Liquid** | ல (la) | ள ($L$a) | ழ (zha) |\n| **Rhotic** | ர (ra) | ற ($R$a) | |"
    },
    {
      "type": "multiple_choice",
      "id": "q10",
      "step_title": "Final Check",
      "question": "Which of these is the 'standard' L?",
      "options": ["ல", "ள", "ழ", "ர"],
      "correct_answer": "ல",
      "feedback": "Correct! **ல** is the standard L."
    }
  ]
}